{
  "configVersion": 1,
  "timestamp": 1755862578660,
  "index": "/dart-board/index.html",
  "assetGroups": [
    {
      "name": "app",
      "installMode": "prefetch",
      "updateMode": "prefetch",
      "cacheQueryOptions": {
        "ignoreVary": true
      },
      "urls": [
        "/dart-board/chunk-4IKJL2TU.js",
        "/dart-board/chunk-EAZYPGFG.js",
        "/dart-board/favicon.ico",
        "/dart-board/index.html",
        "/dart-board/main-J6ITK4WU.js",
        "/dart-board/polyfills-MB6D75FS.js",
        "/dart-board/styles-TE5KCG4P.css"
      ],
      "patterns": []
    },
    {
      "name": "assets",
      "installMode": "lazy",
      "updateMode": "prefetch",
      "cacheQueryOptions": {
        "ignoreVary": true
      },
      "urls": [],
      "patterns": []
    }
  ],
  "dataGroups": [],
  "hashTable": {
    "/dart-board/chunk-4IKJL2TU.js": "934e878647370de9437c6b400b83b89bace7f2de",
    "/dart-board/chunk-EAZYPGFG.js": "0bdcd57fea7e1f294c84c672d5df2e77fc6b85ba",
    "/dart-board/favicon.ico": "22f6a4a3bcaafafb0254e0f2fa4ceb89e505e8b2",
    "/dart-board/index.html": "4d30500e5b664df04be7686cedf9c249e4dae1c1",
    "/dart-board/main-J6ITK4WU.js": "2e9adb51b8df04857659c550b9ab0cc575396cf7",
    "/dart-board/polyfills-MB6D75FS.js": "3b7d0240109066aa8909a470e42d05d162a53c01",
    "/dart-board/styles-TE5KCG4P.css": "b8b393156674f1f4f71fefb2a950dd99600f7dd2"
  },
  "navigationUrls": [
    {
      "positive": true,
      "regex": "^\\/.*$"
    },
    {
      "positive": false,
      "regex": "^\\/(?:.+\\/)?[^/]*\\.[^/]*$"
    },
    {
      "positive": false,
      "regex": "^\\/(?:.+\\/)?[^/]*__[^/]*$"
    },
    {
      "positive": false,
      "regex": "^\\/(?:.+\\/)?[^/]*__[^/]*\\/.*$"
    }
  ],
  "navigationRequestStrategy": "performance"
}